simple_state_tracker/__init__.py
simple_state_tracker/data_model.py
simple_state_tracker/key_model.py
simple_state_tracker/simple_state_tracker.py
simple_state_tracker/simple_state_tracker.py~
simple_state_tracker-0.3.1.dist-info/LICENSE
simple_state_tracker-0.3.1.dist-info/METADATA
simple_state_tracker-0.3.1.dist-info/WHEEL
simple_state_tracker-0.3.1.dist-info/RECORD
