Metadata-Version: 2.3
Name: simple-state-tracker
Version: 0.3.1
Summary: A minimal, type-safe, file-backed state tracker using Pydantic models.
License: LICENSE
Author: Max Chis
Author-email: maxachis@gmail.com
Requires-Python: >=3.9,<4.0
Classifier: License :: Other/Proprietary License
Classifier: Programming Language :: Python :: 3
Classifier: Programming Language :: Python :: 3.9
Classifier: Programming Language :: Python :: 3.10
Classifier: Programming Language :: Python :: 3.11
Classifier: Programming Language :: Python :: 3.12
Classifier: Programming Language :: Python :: 3.13
Requires-Dist: pydantic (>=2.11,<3.0)
Project-URL: Homepage, https://github.com/maxachis/simple-state-tracker
Project-URL: Issues, https://github.com/maxachis/simple-state-tracker/issues
Project-URL: Repository, https://github.com/maxachis/simple-state-tracker
